mongoclasses/__about__.py
mongoclasses/__init__.py
mongoclasses/operations.py
mongoclasses/serialization.py
mongoclasses/types.py
mongoclasses/utils.py
mongoclasses-0.6.0.dist-info/METADATA
mongoclasses-0.6.0.dist-info/WHEEL
mongoclasses-0.6.0.dist-info/licenses/LICENSE.txt
mongoclasses-0.6.0.dist-info/RECORD
