Metadata-Version: 2.1
Name: mongoclasses
Version: 0.6.0
Summary: A lightweight tool for performing MongoDB operations on python dataclasses.
Project-URL: Documentation, https://github.com/rykroon/mongoclasses#readme
Project-URL: Issues, https://github.com/rykroon/mongoclasses/issues
Project-URL: Source, https://github.com/rykroon/mongoclasses
Author-email: Ryan Kroon <rykroon.tech@gmail.com>
License-Expression: MIT
License-File: LICENSE.txt
Classifier: Development Status :: 4 - Beta
Classifier: Programming Language :: Python
Classifier: Programming Language :: Python :: 3.8
Classifier: Programming Language :: Python :: 3.9
Classifier: Programming Language :: Python :: 3.10
Classifier: Programming Language :: Python :: 3.11
Classifier: Programming Language :: Python :: Implementation :: CPython
Classifier: Programming Language :: Python :: Implementation :: PyPy
Requires-Python: >=3.8
Requires-Dist: motor<4,>=3.3.0
Requires-Dist: typing-extensions==4.*
